matrixview.py
matrixview-0.0.5.dist-info/LICENSE
matrixview-0.0.5.dist-info/METADATA
matrixview-0.0.5.dist-info/WHEEL
matrixview-0.0.5.dist-info/top_level.txt
matrixview-0.0.5.dist-info/RECORD
